sblu/__init__.py
sblu/cluspro.py
sblu/cluster.py
sblu/config.py
sblu/ft.py
sblu/grids.py
sblu/job.py
sblu/one_letter.py
sblu/pdb.py
sblu/rmsd.py
sblu/util.py
sblu/version.py
sblu/xyztraj.py
sblu/cli/__init__.py
sblu/cli/main.py
sblu/cli/util.py
sblu/cli/atlas/__init__.py
sblu/cli/atlas/cmd_to_pdb.py
sblu/cli/cluspro/__init__.py
sblu/cli/cluspro/cmd_download.py
sblu/cli/cluspro/cmd_local.py
sblu/cli/cluspro/cmd_minimize.py
sblu/cli/cluspro/cmd_submit.py
sblu/cli/docking/__init__.py
sblu/cli/docking/cmd_cluster.py
sblu/cli/docking/cmd_gen_cluster_pdb.py
sblu/cli/docking/cmd_piper.py
sblu/cli/ftmap/__init__.py
sblu/cli/ftmap/cmd_download.py
sblu/cli/ftmap/cmd_submit.py
sblu/cli/measure/__init__.py
sblu/cli/measure/cmd_evaluate.py
sblu/cli/measure/cmd_ftrmsd.py
sblu/cli/measure/cmd_pwrmsd.py
sblu/cli/measure/cmd_srmsd.py
sblu/cli/pdb/__init__.py
sblu/cli/pdb/cmd_clean.py
sblu/cli/pdb/cmd_get.py
sblu/cli/pdb/cmd_pdb_psf_concat.py
sblu/cli/pdb/cmd_prep.py
sblu/cli/pdb/cmd_psfgen.py
sblu/cli/pdb/cmd_splitsegs.py
sblu/cli/xyztraj/__init__.py
sblu/cli/xyztraj/cmd_gen_cluster_pdb.py
sblu/io/__init__.py
sblu/io/atlas.py
sblu-0.7.2.data/scripts/cl_load_job
sblu-0.7.2.data/scripts/cluspro_local.py
sblu-0.7.2.dist-info/LICENSE
sblu-0.7.2.dist-info/METADATA
sblu-0.7.2.dist-info/WHEEL
sblu-0.7.2.dist-info/entry_points.txt
sblu-0.7.2.dist-info/top_level.txt
sblu-0.7.2.dist-info/RECORD
