Metadata-Version: 2.1
Name: sblu
Version: 0.7.2
Summary: Library for munging data files from ClusPro/FTMap/etc.
Home-page: https://bitbucket.org/bu-structure/sb-lab-utils
Author: Bing Xia
Author-email: sixpi@bu.edu
License: MIT
Keywords: cluspro protein PDB
Platform: UNKNOWN
Classifier: Development Status :: 4 - Beta
Classifier: Intended Audience :: Science/Research
Classifier: License :: OSI Approved :: MIT License
Classifier: Operating System :: MacOS
Classifier: Operating System :: POSIX
Classifier: Programming Language :: Python :: 3.5
Classifier: Programming Language :: Python :: 3.6
Classifier: Programming Language :: Python :: 3.7
Classifier: Topic :: Scientific/Engineering :: Bio-Informatics
Requires-Dist: path.py (>=7.0)
Requires-Dist: numpy (>=1.10)
Requires-Dist: scipy (>=0.16)
Requires-Dist: configobj (>=5.0)
Requires-Dist: click (>=5.1)
Requires-Dist: requests (>=2.4)
Requires-Dist: prody (>=1.8.2)
Requires-Dist: pyparsing (>=2.3)
Requires-Dist: BioPython (>=1.73)
